pybondi/__init__.py
pybondi/callbacks.py
pybondi/commands.py
pybondi/events.py
pybondi/publisher.py
pybondi/service.py
pybondi/session.py
pybondi-2.0.1.dist-info/LICENSE
pybondi-2.0.1.dist-info/METADATA
pybondi-2.0.1.dist-info/WHEEL
pybondi-2.0.1.dist-info/RECORD
