Metadata-Version: 2.3
Name: pybondi
Version: 2.0.1
Summary: A lightweight library for creating message driven systems.
License: MIT
Author: Eric Cardozo
Author-email: eric.m.cardozo@mi.unc.edu.ar
Requires-Python: >=3.12,<4.0
Classifier: License :: OSI Approved :: MIT License
Classifier: Programming Language :: Python :: 3
Classifier: Programming Language :: Python :: 3.12
Classifier: Programming Language :: Python :: 3.13
Requires-Dist: fast-depends (>=2.4.12,<3.0.0)
